Metadata-Version: 2.1
Name: pdfbuilder
Version: 0.1.0
Summary: A package for low-level PDF crafting
Home-page: https://github.com/VadimShmatov/pdfbuilder
Author: Vadim Shmatov
Author-email: shmatov96@mail.ru
License: UNKNOWN
Platform: UNKNOWN
Classifier: Programming Language :: Python :: 3.5
Classifier: License :: OSI Approved :: MIT License
Classifier: Operating System :: OS Independent
Requires-Python: >=3.5
